setup.py
gpglib/__init__.py
gpglib/errors.py
gpglib/packet_parser.py
gpglib/structures.py
gpglib/utils.py
gpglib.egg-info/PKG-INFO
gpglib.egg-info/SOURCES.txt
gpglib.egg-info/dependency_links.txt
gpglib.egg-info/requires.txt
gpglib.egg-info/top_level.txt
gpglib/content_parsers/__init__.py
gpglib/content_parsers/base.py
gpglib/content_parsers/data.py
gpglib/content_parsers/delegators.py
gpglib/content_parsers/keys.py
gpglib/content_parsers/session_keys.py