Metadata-Version: 1.0
Name: gpglib
Version: 0.1.1
Summary: Library for decrypting gpg that doesn't shell out to gpg
Home-page: UNKNOWN
Author: Hitwise
Author-email: nobody@hitwise.com
License: LGPLv2
Keywords: gpg decrypt
Platform: UNKNOWN
